ppi/__init__.py
ppi/core/initialize_db.py
ppi/core/ppi_analyzer.py
ppi/core/ppi_data_manager.py
ppi/core/ppi_searcher.py
ppi/core/ppi_visualizer.py
ppi/core/utils/download_metadata.py
ppi/core/utils/download_series_data.py
ppi/db_models/commodity_data.py
ppi/db_models/metadata.py
ppi_toolkit-0.1.6.dist-info/LICENSE
ppi_toolkit-0.1.6.dist-info/METADATA
ppi_toolkit-0.1.6.dist-info/WHEEL
ppi_toolkit-0.1.6.dist-info/entry_points.txt
ppi_toolkit-0.1.6.dist-info/RECORD
