Metadata-Version: 2.1
Name: ppi-toolkit
Version: 0.1.6
Summary: A toolkit for working with Producer Price Index (PPI) data
Author: justin
Author-email: justinjagoss@gmail.com
Requires-Python: >=3.12,<4.0
Classifier: Programming Language :: Python :: 3
Classifier: Programming Language :: Python :: 3.12
Requires-Dist: fuzzywuzzy (>=0.18.0,<0.19.0)
Requires-Dist: matplotlib (>=3.10.0,<4.0.0)
Requires-Dist: numpy (>=1.23,<2.0)
Requires-Dist: pandas (>=2.2.3,<3.0.0)
Requires-Dist: pandera (>=0.22.1,<0.23.0)
Requires-Dist: pydantic (>=2.10.6,<3.0.0)
Requires-Dist: requests (>=2.32.3,<3.0.0)
Requires-Dist: sqlalchemy (>=2.0.0,<3.0.0)
